bio2bel_hsdn/__init__.py
bio2bel_hsdn/__main__.py
bio2bel_hsdn/cli.py
bio2bel_hsdn/constants.py
bio2bel_hsdn/manager.py
bio2bel_hsdn/models.py
bio2bel_hsdn/parser.py
bio2bel_hsdn-0.0.1.dist-info/LICENSE
bio2bel_hsdn-0.0.1.dist-info/METADATA
bio2bel_hsdn-0.0.1.dist-info/WHEEL
bio2bel_hsdn-0.0.1.dist-info/entry_points.txt
bio2bel_hsdn-0.0.1.dist-info/top_level.txt
bio2bel_hsdn-0.0.1.dist-info/RECORD
