Metadata-Version: 2.1
Name: bio2bel-hsdn
Version: 0.0.1
Summary: Converts the human symptoms-disease network produced by Zhou and Himmelstein to BEL
Home-page: https://github.com/bio2bel/hsdn
Author: Charles Tapley Hoyt
Author-email: cthoyt@gmail.com
Maintainer: Charles Tapley Hoyt
Maintainer-email: cthoyt@gmail.com
License: MIT
Download-URL: https://github.com/bio2bel/hsdn/releases
Project-URL: Bug Tracker, https://github.com/bio2bel/hsdn/issues
Project-URL: Source Code, https://github.com/bio2bel/hsdn
Keywords: Biological Expression Language,Bio2BEL
Platform: UNKNOWN
Classifier: Development Status :: 1 - Planning
Classifier: Intended Audience :: Developers
Classifier: Intended Audience :: Science/Research
Classifier: Programming Language :: Python
Classifier: Programming Language :: Python :: 3.7
Classifier: Programming Language :: Python :: 3.6
Classifier: Programming Language :: Python :: 3 :: Only
Classifier: License :: OSI Approved :: MIT License
Classifier: Topic :: Scientific/Engineering :: Chemistry
Classifier: Topic :: Scientific/Engineering :: Bio-Informatics
Requires-Python: >=3.6
Requires-Dist: bio2bel
Requires-Dist: pybel
Requires-Dist: sqlalchemy
Requires-Dist: tqdm
Provides-Extra: docs
Requires-Dist: sphinx ; extra == 'docs'
Requires-Dist: sphinx-rtd-theme ; extra == 'docs'
Requires-Dist: sphinx-click ; extra == 'docs'
Requires-Dist: sphinx-autodoc-typehints ; extra == 'docs'
